{
  "maps": [
    {
      "id": "swiss_alps",
      "name": "Swiss Alps",
      "desc": "Classic alpine bowls, pine forests and long groomed descents beneath towering peaks.",
      "unlockLevel": 1,
      "seed": 1337,
      "timeOfDay": "cycle",
      "startTime": 0.3,
      "weatherSet": ["sunny", "cloudy", "snow", "heavysnow", "fog"],
      "startWeather": "sunny",
      "palette": {
        "snow": "#eef4fb",
        "snowShadow": "#b9cbe4",
        "ice": "#9fd8f0",
        "rock": "#5d6470",
        "tree": "#2f5d46",
        "trunk": "#5a4634",
        "skyTop": "#2f6fce",
        "skyHorizon": "#cfe6f7",
        "sunColor": "#fff2d8",
        "fog": "#cfdff0",
        "crystal": "#7fe3ff",
        "neon": "#ffb347"
      },
      "terrain": {
        "slope": 0.34,
        "amp": 26,
        "ridgeAmp": 42,
        "roughness": 0.52,
        "iceRatio": 0.30,
        "lakeLevel": null,
        "island": false
      },
      "density": { "tree": 1.0, "rock": 0.7, "spike": 0.15, "crystal": 0.8, "ring": 0.6, "ramp": 0.7, "pad": 0.3 },
      "medals": { "gold": 95, "silver": 120, "bronze": 160 }
    },
    {
      "id": "arctic",
      "name": "Arctic Circle",
      "desc": "Endless polar plains, frozen lakes and black ice under the dancing northern lights.",
      "unlockLevel": 2,
      "seed": 8181,
      "timeOfDay": "night",
      "startTime": 0.86,
      "weatherSet": ["aurora", "snow", "fog", "blizzard"],
      "startWeather": "aurora",
      "palette": {
        "snow": "#dbe7f5",
        "snowShadow": "#8aa3c8",
        "ice": "#7fc4e8",
        "rock": "#48505e",
        "tree": "#274b3f",
        "trunk": "#4a3a2c",
        "skyTop": "#061024",
        "skyHorizon": "#1d3a5f",
        "sunColor": "#cfe0ff",
        "fog": "#132743",
        "crystal": "#8ff7d0",
        "neon": "#66ffc2"
      },
      "terrain": {
        "slope": 0.22,
        "amp": 14,
        "ridgeAmp": 18,
        "roughness": 0.4,
        "iceRatio": 0.55,
        "lakeLevel": -6,
        "island": false
      },
      "density": { "tree": 0.25, "rock": 0.6, "spike": 0.5, "crystal": 1.0, "ring": 0.5, "ramp": 0.5, "pad": 0.3 },
      "medals": { "gold": 88, "silver": 112, "bronze": 150 }
    },
    {
      "id": "crystal_caves",
      "name": "Crystal Glacier Kingdom",
      "desc": "A violet twilight realm of giant crystals, glassy ice and glittering caverns.",
      "unlockLevel": 3,
      "seed": 4242,
      "timeOfDay": "sunset",
      "startTime": 0.68,
      "weatherSet": ["sunny", "fog", "snow"],
      "startWeather": "sunny",
      "palette": {
        "snow": "#e6ddfa",
        "snowShadow": "#a893d6",
        "ice": "#c49bf0",
        "rock": "#4d3f6b",
        "tree": "#3a2f63",
        "trunk": "#443764",
        "skyTop": "#2a1758",
        "skyHorizon": "#e08cc0",
        "sunColor": "#ffd9f2",
        "fog": "#8f6bb5",
        "crystal": "#e58cff",
        "neon": "#c86bff"
      },
      "terrain": {
        "slope": 0.38,
        "amp": 30,
        "ridgeAmp": 55,
        "roughness": 0.62,
        "iceRatio": 0.45,
        "lakeLevel": null,
        "island": false
      },
      "density": { "tree": 0.15, "rock": 1.0, "spike": 1.4, "crystal": 1.6, "ring": 0.8, "ramp": 0.8, "pad": 0.5 },
      "medals": { "gold": 100, "silver": 128, "bronze": 170 }
    },
    {
      "id": "frozen_city",
      "name": "Neon Ice City",
      "desc": "A frozen metropolis at night — carve past glowing towers on streets of black ice.",
      "unlockLevel": 5,
      "seed": 9099,
      "timeOfDay": "night",
      "startTime": 0.9,
      "weatherSet": ["aurora", "snow", "fog"],
      "startWeather": "snow",
      "palette": {
        "snow": "#d5dced",
        "snowShadow": "#7c88ad",
        "ice": "#79e0f2",
        "rock": "#303748",
        "tree": "#1f4a52",
        "trunk": "#3c3f52",
        "skyTop": "#050914",
        "skyHorizon": "#302a55",
        "sunColor": "#b9d5ff",
        "fog": "#171d33",
        "crystal": "#59f0ff",
        "neon": "#ff4fd8"
      },
      "terrain": {
        "slope": 0.28,
        "amp": 18,
        "ridgeAmp": 26,
        "roughness": 0.45,
        "iceRatio": 0.6,
        "lakeLevel": null,
        "island": false,
        "city": true
      },
      "density": { "tree": 0.1, "rock": 0.3, "spike": 0.4, "crystal": 1.2, "ring": 1.1, "ramp": 1.0, "pad": 0.8 },
      "medals": { "gold": 92, "silver": 118, "bronze": 155 }
    },
    {
      "id": "ice_volcano",
      "name": "Ice Volcano",
      "desc": "Steep obsidian ridges and glowing fissures where fire sleeps beneath the frost.",
      "unlockLevel": 7,
      "seed": 6660,
      "timeOfDay": "sunset",
      "startTime": 0.74,
      "weatherSet": ["cloudy", "fog", "heavysnow"],
      "startWeather": "cloudy",
      "palette": {
        "snow": "#e3e0e2",
        "snowShadow": "#9b8f96",
        "ice": "#9ccfe0",
        "rock": "#2e2a2e",
        "tree": "#3d4a3a",
        "trunk": "#3a3232",
        "skyTop": "#3a1d33",
        "skyHorizon": "#ff9b54",
        "sunColor": "#ffc07a",
        "fog": "#6b4a52",
        "crystal": "#ffb35c",
        "neon": "#ff6b3d"
      },
      "terrain": {
        "slope": 0.44,
        "amp": 34,
        "ridgeAmp": 70,
        "roughness": 0.7,
        "iceRatio": 0.25,
        "lakeLevel": null,
        "island": false
      },
      "density": { "tree": 0.3, "rock": 1.4, "spike": 1.0, "crystal": 0.9, "ring": 0.7, "ramp": 1.0, "pad": 0.6 },
      "medals": { "gold": 105, "silver": 135, "bronze": 175 }
    },
    {
      "id": "floating_glaciers",
      "name": "Floating Glaciers",
      "desc": "Shattered ice islands drifting above an endless sea of cloud. Mind the gaps.",
      "unlockLevel": 9,
      "seed": 2718,
      "timeOfDay": "cycle",
      "startTime": 0.35,
      "weatherSet": ["sunny", "cloudy", "snow"],
      "startWeather": "sunny",
      "palette": {
        "snow": "#f2f7ff",
        "snowShadow": "#a8c4e8",
        "ice": "#8fd4f5",
        "rock": "#57687d",
        "tree": "#2f5d46",
        "trunk": "#5a4634",
        "skyTop": "#1e5bb8",
        "skyHorizon": "#ffe1ef",
        "sunColor": "#fff0cf",
        "fog": "#d9e6fa",
        "crystal": "#9fe8ff",
        "neon": "#7ab8ff"
      },
      "terrain": {
        "slope": 0.3,
        "amp": 24,
        "ridgeAmp": 38,
        "roughness": 0.55,
        "iceRatio": 0.4,
        "lakeLevel": null,
        "island": true
      },
      "density": { "tree": 0.4, "rock": 0.6, "spike": 0.4, "crystal": 1.2, "ring": 1.2, "ramp": 0.9, "pad": 0.9 },
      "medals": { "gold": 110, "silver": 140, "bronze": 185 }
    },
    {
      "id": "sky_islands",
      "name": "Sky Glacier Islands",
      "desc": "Vertigo-inducing island peaks connected by boost rings and leaps of faith.",
      "unlockLevel": 12,
      "seed": 3141,
      "timeOfDay": "sunset",
      "startTime": 0.7,
      "weatherSet": ["sunny", "cloudy"],
      "startWeather": "sunny",
      "palette": {
        "snow": "#fdf2ec",
        "snowShadow": "#d3a8b8",
        "ice": "#a8d8f0",
        "rock": "#6b5a68",
        "tree": "#3f6b4a",
        "trunk": "#5a4634",
        "skyTop": "#472a75",
        "skyHorizon": "#ff9e80",
        "sunColor": "#ffd9a0",
        "fog": "#e8b39a",
        "crystal": "#ffd27f",
        "neon": "#ff9e3d"
      },
      "terrain": {
        "slope": 0.36,
        "amp": 32,
        "ridgeAmp": 60,
        "roughness": 0.6,
        "iceRatio": 0.35,
        "lakeLevel": null,
        "island": true
      },
      "density": { "tree": 0.3, "rock": 0.7, "spike": 0.6, "crystal": 1.4, "ring": 1.5, "ramp": 1.1, "pad": 1.0 },
      "medals": { "gold": 115, "silver": 150, "bronze": 195 }
    },
    {
      "id": "cyber_ice_city",
      "name": "Cyber Ice Metropolis",
      "desc": "The far-future frost grid. Maximum speed, maximum neon, zero mercy.",
      "unlockLevel": 15,
      "seed": 7777,
      "timeOfDay": "night",
      "startTime": 0.92,
      "weatherSet": ["aurora", "fog"],
      "startWeather": "aurora",
      "palette": {
        "snow": "#c9d6ec",
        "snowShadow": "#5f6f9e",
        "ice": "#63f2ff",
        "rock": "#232941",
        "tree": "#15414e",
        "trunk": "#2d3350",
        "skyTop": "#03040c",
        "skyHorizon": "#3d1b66",
        "sunColor": "#a8c8ff",
        "fog": "#0e1230",
        "crystal": "#4dffdb",
        "neon": "#00e5ff"
      },
      "terrain": {
        "slope": 0.4,
        "amp": 22,
        "ridgeAmp": 34,
        "roughness": 0.5,
        "iceRatio": 0.75,
        "lakeLevel": null,
        "island": false,
        "city": true
      },
      "density": { "tree": 0.05, "rock": 0.4, "spike": 0.7, "crystal": 1.5, "ring": 1.6, "ramp": 1.3, "pad": 1.1 },
      "medals": { "gold": 85, "silver": 108, "bronze": 145 }
    }
  ]
}
